setup.py
src/vw.pyx
src/vw_c.cpp
vowpal_porpoise/__init__.py
vowpal_porpoise/sklearn.py
vowpal_porpoise/vp_utils.py
vowpal_porpoise/vw.py
vowpal_porpoise.egg-info/PKG-INFO
vowpal_porpoise.egg-info/SOURCES.txt
vowpal_porpoise.egg-info/dependency_links.txt
vowpal_porpoise.egg-info/requires.txt
vowpal_porpoise.egg-info/top_level.txt