Metadata-Version: 1.1
Name: vowpal-porpoise
Version: 0.3
Summary: Lightweight vowpal wabbit wrapper
Home-page: https://github.com/josephreisinger/vowpal_porpoise
Author: Joseph Reisinger
Author-email: joeraii@gmail.com
License: BSD
Keywords: machine learning regression vowpal_wabbit
Platform: UNKNOWN
Classifier: Development Status :: 4 - Beta
Classifier: Intended Audience :: Science/Research
Classifier: License :: OSI Approved :: BSD License
Classifier: Operating System :: OS Independent
Classifier: Programming Language :: Python
Classifier: Topic :: Scientific/Engineering :: Artificial Intelligence
